README.md
setup.cfg
setup.py
mekoramaqr/__init__.py
mekoramaqr/__main__.py
mekoramaqr/blocks.py
mekoramaqr/mekolevel.py
mekoramaqr/mekoqr.py
mekoramaqr/qrcard.py
mekoramaqr.egg-info/PKG-INFO
mekoramaqr.egg-info/SOURCES.txt
mekoramaqr.egg-info/dependency_links.txt
mekoramaqr.egg-info/entry_points.txt
mekoramaqr.egg-info/requires.txt
mekoramaqr.egg-info/top_level.txt
mekoramaqr/test/__init__.py
mekoramaqr/test/test_reading.py